wormhole/__init__.py
wormhole/__main__.py
wormhole/ad_blocker.py
wormhole/auth_manager.py
wormhole/authentication.py
wormhole/context.py
wormhole/handler.py
wormhole/logger.py
wormhole/network_monitor.py
wormhole/proxy.py
wormhole/resolver.py
wormhole/safeguards.py
wormhole/server.py
wormhole/tools.py
wormhole/version.py
wormhole_proxy-3.5.0.dist-info/LICENSE
wormhole_proxy-3.5.0.dist-info/METADATA
wormhole_proxy-3.5.0.dist-info/WHEEL
wormhole_proxy-3.5.0.dist-info/entry_points.txt
wormhole_proxy-3.5.0.dist-info/RECORD
