Metadata-Version: 2.3
Name: wormhole-proxy
Version: 3.5.0
Summary: Asynchronous I/O HTTP and HTTPS Proxy on Python >= 3.11
License: MIT
Keywords: wormhole,asynchronous,web,proxy
Author: Chaiwat Suttipongsakul
Author-email: cwt@bashell.com
Requires-Python: >=3.11
Classifier: Development Status :: 5 - Production/Stable
Classifier: Environment :: Console
Classifier: Intended Audience :: Information Technology
Classifier: Intended Audience :: System Administrators
Classifier: License :: OSI Approved :: MIT License
Classifier: Operating System :: POSIX
Classifier: Operating System :: Microsoft :: Windows
Classifier: Programming Language :: Python :: 3.11
Classifier: Programming Language :: Python :: 3.12
Classifier: Programming Language :: Python :: 3.13
Classifier: Topic :: Internet :: Proxy Servers
Provides-Extra: performance
Requires-Dist: aiodns (>=3.5,<4.0)
Requires-Dist: aiohttp (>=3.12,<4.0)
Requires-Dist: aiosqlite (>=0.21,<0.22)
Requires-Dist: loguru (>=0.7,<0.8)
Requires-Dist: pywin32 ; sys_platform == "win32"
Requires-Dist: uvloop ; extra == "performance"
Requires-Dist: winloop ; extra == "performance"
Project-URL: Homepage, https://hg.sr.ht/~cwt/wormhole
